COPYING
LICENSE
MANIFEST.in
README.rst
setup.py
cmsplugin_markup/__init__.py
cmsplugin_markup/cms_plugins.py
cmsplugin_markup/forms.py
cmsplugin_markup/models.py
cmsplugin_markup/urls.py
cmsplugin_markup.egg-info/PKG-INFO
cmsplugin_markup.egg-info/SOURCES.txt
cmsplugin_markup.egg-info/dependency_links.txt
cmsplugin_markup.egg-info/not-zip-safe
cmsplugin_markup.egg-info/requires.txt
cmsplugin_markup.egg-info/top_level.txt
cmsplugin_markup/conf/__init__.py
cmsplugin_markup/conf/global_settings.py
cmsplugin_markup/migrations/0001_initial.py
cmsplugin_markup/migrations/0002_auto__add_field_markupfield_body_scripts__add_field_markupfield_body_s.py
cmsplugin_markup/migrations/0003_auto__add_field_markupfield_css_class.py
cmsplugin_markup/migrations/__init__.py
cmsplugin_markup/plugins/__init__.py
cmsplugin_markup/plugins/base.py
cmsplugin_markup/plugins/markdown/__init__.py
cmsplugin_markup/plugins/markdown/mark_down.py
cmsplugin_markup/plugins/markdown/conf/__init__.py
cmsplugin_markup/plugins/markdown/conf/global_settings.py
cmsplugin_markup/plugins/restructuredtext/__init__.py
cmsplugin_markup/plugins/textile/__init__.py
cmsplugin_markup/static/cmsplugin_markup/grip.png
cmsplugin_markup/static/cmsplugin_markup/markup.css
cmsplugin_markup/static/cmsplugin_markup/markup.js
cmsplugin_markup/static/cmsplugin_markup/markup_admin.js
cmsplugin_markup/templates/cmsplugin_markup/markup.html
cmsplugin_markup/templates/cmsplugin_markup/markup_plugin_change_form.html
cmsplugin_markup/templatetags/__init__.py
cmsplugin_markup/templatetags/markuptags.py
cmsplugin_markup/utils/__init__.py
cmsplugin_markup/utils/markup.py
cmsplugin_markup/utils/plugins.py
docs/Makefile
docs/conf.py
docs/index.rst
docs/plugins.rst