Metadata-Version: 1.0
Name: cmsplugin-markup
Version: 0.2.2
Summary: Extendable markup content plugin for Django CMS.
Home-page: https://bitbucket.org/mitar/cmsplugin-markup
Author: Mitar
Author-email: mitar.django@tnode.com
License: AGPLv3
Platform: UNKNOWN
Classifier: Development Status :: 4 - Beta
Classifier: Environment :: Web Environment
Classifier: Intended Audience :: Developers
Classifier: License :: OSI Approved :: GNU Affero General Public License v3
Classifier: Operating System :: OS Independent
Classifier: Programming Language :: Python
Classifier: Framework :: Django
